na/__init__.py
na-0.0.6.dist-info/licenses/LICENSE
na-0.0.6.dist-info/METADATA
na-0.0.6.dist-info/WHEEL
na-0.0.6.dist-info/top_level.txt
na-0.0.6.dist-info/RECORD
