Metadata-Version: 2.4
Name: na
Version: 0.0.6
Summary: Functions and script to peek into the callable/argument structure of a set of callables
Home-page: https://github.com/t-c-w/na
Author: Thor Whalen
License: apache-2.0
Platform: any
License-File: LICENSE
Dynamic: license-file
